{
	"Prized Baseball Cards": [{
		"Player": "Roberto Clemente",
		"Team": "Pittsburgh Pirates",
		"Brand": "Topps",
		"Year": "1957"
	},
	{
		"Player": "Jackie Robinson",
		"Team": "Brooklyn Dodgers",
		"Brand": "Dodgers",
		"Year": "1954"
	},
	{
		"Player": "Hank Aaron",
		"Team": "Milwaukee Braves",
		"Brand": "Topps",
		"Year": "1959"
	},
	{
		"Player": " J.T Meyers",
		"Team": "New York Giants",
		"Brand": "Turkey Red Cigarettes",
		"Year": "1909"
	},
	{
		"Player": "David Arias (Ortiz)",
		"Team": "Minnesota Twins",
		"Brand": "Fleer Ultra",
		"Year": "1997"
	}]
	
}